Workbook
Name aporte: Simulador!$D$15
Name aporte_sugerido: Simulador!$D$9
Name salario: Simulador!$D$7
Name taxa_mensal: Simulador!$D$17

Sheet Simulador
B2: FII | PLANEJADOR DE PATRIMÔNIO
B4: Simule aportes mensais, renda passiva e alocação por perfil • valores nominais
B6: 01 CONFIGURAÇÕES
B7: Salário mensal (R$) | D7: 5000
B8: Rendimento mensal da carteira | D8: 0.006
B9: Aporte sugerido (30% do salário) | D9: =D7*D10 -> 1500
B10: Percentual sugerido do salário | D10: 0.3
B13: 02 SIMULAÇÃO PRINCIPAL | H13: SIMULAÇÃO COM 30% DO SALÁRIO
B15: Quanto investir por mês? (R$) | D15: 500 | H15: Aporte mensal sugerido | I15: =aporte_sugerido -> 1500
B16: Por quantos anos? | D16: 5 | H16: Prazo (anos) | I16: =D16 -> 5
B17: Taxa de rendimento mensal | D17: =D8 -> 0.006 | H17: Rendimento mensal | I17: =taxa_mensal -> 0.006
B18: Patrimônio acumulado (R$) | D18: =FV(taxa_mensal,D16*12,-aporte,0,0) -> 35982.368 | H18: Patrimônio estimado | I18: =FV(taxa_mensal,I16*12,-I15,0,0) -> 107947.1
B19: Dividendos mensais estimados (R$) | D19: =D18*taxa_mensal -> 215.89421 | H19: Dividendos por mês | I19: =I18*taxa_mensal -> 647.68262
B20: Total de aportes (R$) | D20: =aporte*D16*12 -> 30000 | H20: Total aportado | I20: =I15*I16*12 -> 90000
B21: Rendimentos acumulados (R$) | D21: =D18-D20 -> 5982.3677 | H21: Rendimentos acumulados | I21: =I18-I20 -> 17947.103
B22: Perfil de investidor | D22: Moderado
B25: 03 CENÁRIOS DE LONGO PRAZO
B27: Prazo (anos) | C27: Aporte mensal (R$) | D27: Total investido (R$) | E27: Patrimônio final (R$) | F27: Dividendos/mês (R$) | H27: Prazo (anos) | I27: Aporte sugerido (R$) | J27: Patrimônio final (R$) | K27: Dividendos/mês (R$)
B28: 2 | C28: =aporte -> 500 | D28: =C28*B28*12 -> 12000 | E28: =FV(taxa_mensal,B28*12,-C28,0,0) -> 12865.608 | F28: =E28*taxa_mensal -> 77.193646 | H28: =B28 -> 2 | I28: =aporte_sugerido -> 1500 | J28: =FV(taxa_mensal,H28*12,-I28,0,0) -> 38596.823 | K28: =J28*taxa_mensal -> 231.58094
B29: 5 | C29: =aporte -> 500 | D29: =C29*B29*12 -> 30000 | E29: =FV(taxa_mensal,B29*12,-C29,0,0) -> 35982.368 | F29: =E29*taxa_mensal -> 215.89421 | H29: =B29 -> 5 | I29: =aporte_sugerido -> 1500 | J29: =FV(taxa_mensal,H29*12,-I29,0,0) -> 107947.1 | K29: =J29*taxa_mensal -> 647.68262
B30: 10 | C30: =aporte -> 500 | D30: =C30*B30*12 -> 60000 | E30: =FV(taxa_mensal,B30*12,-C30,0,0) -> 87501.505 | F30: =E30*taxa_mensal -> 525.00903 | H30: =B30 -> 10 | I30: =aporte_sugerido -> 1500 | J30: =FV(taxa_mensal,H30*12,-I30,0,0) -> 262504.51 | K30: =J30*taxa_mensal -> 1575.0271
B31: 20 | C31: =aporte -> 500 | D31: =C31*B31*12 -> 120000 | E31: =FV(taxa_mensal,B31*12,-C31,0,0) -> 266881.17 | F31: =E31*taxa_mensal -> 1601.287 | H31: =B31 -> 20 | I31: =aporte_sugerido -> 1500 | J31: =FV(taxa_mensal,H31*12,-I31,0,0) -> 800643.51 | K31: =J31*taxa_mensal -> 4803.861
B32: 30 | C32: =aporte -> 500 | D32: =C32*B32*12 -> 180000 | E32: =FV(taxa_mensal,B32*12,-C32,0,0) -> 634612.72 | F32: =E32*taxa_mensal -> 3807.6763 | H32: =B32 -> 30 | I32: =aporte_sugerido -> 1500 | J32: =FV(taxa_mensal,H32*12,-I32,0,0) -> 1903838.2 | K32: =J32*taxa_mensal -> 11423.029
B37: 04 ALOCAÇÃO DE FIIs POR PERFIL
B39: Tipo de FII | C39: % da carteira | D39: Aporte mensal (R$) | E39: Perfil selecionado
B40: PAPEL | C40: =VLOOKUP($D$22&"-"&B40,Apoio!$B$3:$E$20,4,FALSE) -> 0.32 | D40: =aporte*C40 -> 160 | E40: =$D$22 -> Moderado
B41: TIJOLO | C41: =VLOOKUP($D$22&"-"&B41,Apoio!$B$3:$E$20,4,FALSE) -> 0.35 | D41: =aporte*C41 -> 175 | E41: =$D$22 -> Moderado
B42: HÍBRIDOS | C42: =VLOOKUP($D$22&"-"&B42,Apoio!$B$3:$E$20,4,FALSE) -> 0.08 | D42: =aporte*C42 -> 40 | E42: =$D$22 -> Moderado
B43: FOFs | C43: =VLOOKUP($D$22&"-"&B43,Apoio!$B$3:$E$20,4,FALSE) -> 0.05 | D43: =aporte*C43 -> 25 | E43: =$D$22 -> Moderado
B44: DESENVOLVIMENTO | C44: =VLOOKUP($D$22&"-"&B44,Apoio!$B$3:$E$20,4,FALSE) -> 0.1 | D44: =aporte*C44 -> 50 | E44: =$D$22 -> Moderado
B45: HOTELARIAS | C45: =VLOOKUP($D$22&"-"&B45,Apoio!$B$3:$E$20,4,FALSE) -> 0.1 | D45: =aporte*C45 -> 50 | E45: =$D$22 -> Moderado
B46: TOTAL | C46: =SUM(C40:C45) -> 1 | D46: =SUM(D40:D45) -> 500
B48: Premissas ilustrativas: rendimento e dividendos são estimativas constantes, antes de impostos, custos e inflação; não há garantia de retorno.

Sheet Apoio
B2: CHAVE | C2: PERFIL | D2: TIPO DE FII | E2: PERCENTUAL | G2: Perfis / lista
B3: Conservador-PAPEL | C3: Conservador | D3: PAPEL | E3: 0.3 | G3: Conservador
B4: Conservador-TIJOLO | C4: Conservador | D4: TIJOLO | E4: 0.5 | G4: Moderado
B5: Conservador-HÍBRIDOS | C5: Conservador | D5: HÍBRIDOS | E5: 0.1 | G5: Agressivo
B6: Conservador-FOFs | C6: Conservador | D6: FOFs | E6: 0.1
B7: Conservador-DESENVOLVIMENTO | C7: Conservador | D7: DESENVOLVIMENTO | E7: 0 | G7: Origem dos pesos: arquivo modelo fornecido.
B8: Conservador-HOTELARIAS | C8: Conservador | D8: HOTELARIAS | E8: 0 | G8: Agressivo: pesos completados para somar 100%.
B9: Moderado-PAPEL | C9: Moderado | D9: PAPEL | E9: 0.32 | G9: Premissas editáveis; não representam recomendação.
B10: Moderado-TIJOLO | C10: Moderado | D10: TIJOLO | E10: 0.35
B11: Moderado-HÍBRIDOS | C11: Moderado | D11: HÍBRIDOS | E11: 0.08
B12: Moderado-FOFs | C12: Moderado | D12: FOFs | E12: 0.05
B13: Moderado-DESENVOLVIMENTO | C13: Moderado | D13: DESENVOLVIMENTO | E13: 0.1
B14: Moderado-HOTELARIAS | C14: Moderado | D14: HOTELARIAS | E14: 0.1
B15: Agressivo-PAPEL | C15: Agressivo | D15: PAPEL | E15: 0.5
B16: Agressivo-TIJOLO | C16: Agressivo | D16: TIJOLO | E16: 0.1
B17: Agressivo-HÍBRIDOS | C17: Agressivo | D17: HÍBRIDOS | E17: 0.05
B18: Agressivo-FOFs | C18: Agressivo | D18: FOFs | E18: 0.05
B19: Agressivo-DESENVOLVIMENTO | C19: Agressivo | D19: DESENVOLVIMENTO | E19: 0.2
B20: Agressivo-HOTELARIAS | C20: Agressivo | D20: HOTELARIAS | E20: 0.1
